stapi_fastapi/__init__.py
stapi_fastapi/conformance.py
stapi_fastapi/constants.py
stapi_fastapi/errors.py
stapi_fastapi/py.typed
stapi_fastapi/responses.py
stapi_fastapi/backends/__init__.py
stapi_fastapi/backends/product_backend.py
stapi_fastapi/backends/root_backend.py
stapi_fastapi/models/__init__.py
stapi_fastapi/models/product.py
stapi_fastapi/models/root.py
stapi_fastapi/routers/__init__.py
stapi_fastapi/routers/base.py
stapi_fastapi/routers/product_router.py
stapi_fastapi/routers/root_router.py
stapi_fastapi/routers/route_names.py
stapi_fastapi/routers/utils.py
stapi_fastapi-0.8.0.dist-info/METADATA
stapi_fastapi-0.8.0.dist-info/WHEEL
stapi_fastapi-0.8.0.dist-info/RECORD
