Metadata-Version: 2.4
Name: stapi-fastapi
Version: 0.8.0
Summary: Sensor Tasking API (STAPI) with FastAPI
Author-email: Christian Wygoda <christian.wygoda@wygoda.net>, Phil Varner <phil@philvarner.com>
License-Expression: MIT
Requires-Python: >=3.11
Requires-Dist: fastapi>=0.115.0
Requires-Dist: geojson-pydantic>=1.1
Requires-Dist: httpx>=0.27.0
Requires-Dist: nox>=2024.4.15
Requires-Dist: pydantic-settings>=2.2.1
Requires-Dist: pydantic>=2.10
Requires-Dist: pygeofilter>=0.2
Requires-Dist: returns>=0.23
Requires-Dist: stapi-pydantic>=0.1.0
Requires-Dist: uvicorn>=0.29.0
